COPYING
COPYING.lesser
MANIFEST.in
README.md
runtests.py
setup.py
leftrb/__init__.py
leftrb/bst.py
leftrb/llrb.py
leftrb.egg-info/PKG-INFO
leftrb.egg-info/SOURCES.txt
leftrb.egg-info/dependency_links.txt
leftrb.egg-info/requires.txt
leftrb.egg-info/top_level.txt
leftrb/test/__init__.py
leftrb/test/test_bst.py
leftrb/test/test_llrb.py