Metadata-Version: 1.1
Name: leftrb
Version: 0.1.3
Summary: Leftrb is a Left-Leaning Red-Black (LLRB) implementation of 2–3 balanced binary
